Workbook

Sheet Campaign_Data
A1: 🏥 Diabetes Awareness Campaign — City-wise Dataset
A2: City | B2: People Reached | C2: People Screened | D2: Diabetes Diagnosed | E2: Patients Treated | F2: Campaign Cost (₹)
A3: Delhi | B3: 10000 | C3: 2000 | D3: 350 | E3: 220 | F3: 150000
A4: Mumbai | B4: 9000 | C4: 1800 | D4: 320 | E4: 210 | F4: 140000
A5: Bangalore | B5: 8500 | C5: 1600 | D5: 300 | E5: 190 | F5: 135000
A6: Chennai | B6: 8000 | C6: 1500 | D6: 270 | E6: 170 | F6: 130000
A7: Hyderabad | B7: 7800 | C7: 1400 | D7: 250 | E7: 160 | F7: 125000
A8: Pune | B8: 7500 | C8: 1350 | D8: 240 | E8: 150 | F8: 120000
A9: Ahmedabad | B9: 7200 | C9: 1300 | D9: 230 | E9: 145 | F9: 115000
A10: Kolkata | B10: 7000 | C10: 1200 | D10: 210 | E10: 130 | F10: 110000
A11: Lucknow | B11: 6800 | C11: 1150 | D11: 200 | E11: 120 | F11: 105000
A12: Jaipur | B12: 6500 | C12: 1100 | D12: 190 | E12: 115 | F12: 100000
A13: Chandigarh | B13: 6000 | C13: 1000 | D13: 170 | E13: 100 | F13: 95000
A14: Indore | B14: 5800 | C14: 950 | D14: 160 | E14: 95 | F14: 90000
... A22: Guwahati | B22: 4200 | C22: 620 | D22: 90 | E22: 55 | F22: 68000
A23: TOTAL | B23: =SUM(B3:B22) -> 129300 | C23: =SUM(C3:C22) -> 22420 | D23: =SUM(D3:D22) -> 3865 | E23: =SUM(E3:E22) -> 2388 | F23: =SUM(F3:F22) -> 2018000

Sheet Campaign_Summary
A1: 📊 Campaign Summary — Key Metrics
A2: Metric | B2: Formula Used | C2: Value
A3: Total People Reached | B3: SUM(People Reached — all cities) | C3: =SUM(Campaign_Data!B3:B22) -> 129300
A4: Total People Screened | B4: SUM(People Screened — all cities) | C4: =SUM(Campaign_Data!C3:C22) -> 22420
A5: Total Diagnosed | B5: SUM(Diabetes Diagnosed — all cities) | C5: =SUM(Campaign_Data!D3:D22) -> 3865
A6: Total Patients Treated | B6: SUM(Patients Treated — all cities) | C6: =SUM(Campaign_Data!E3:E22) -> 2388
A7: Total Campaign Cost | B7: SUM(Campaign Cost — all cities) | C7: =SUM(Campaign_Data!F3:F22) -> 2018000
A9: --- Derived KPIs ---
A10: Screening Rate | B10: Derived from summary | C10: =C4/C3 -> 0.1733952
A11: Diagnosis Rate (screened) | B11: Derived from summary | C11: =C5/C4 -> 0.17239072
A12: Treatment Rate (diagnosed) | B12: Derived from summary | C12: =C6/C5 -> 0.61785252
A13: Overall Conversion Rate | B13: Derived from summary | C13: =C6/C3 -> 0.018468677

Sheet Revenue_Model
A1: 💰 Revenue Model — Diabetes Medicine
A2: Metric | B2: Details / Formula | C2: Value
A3: Avg Monthly Medicine Cost | B3: Assumption (hardcoded input) | C3: 650
A4: Annual Revenue / Patient | B4: Annual Revenue Per Patient = Monthly Cost x 12 | C4: =C3*12 -> 7800
A5: Total Patients Treated | B5: Linked from Campaign_Summary | C5: =Campaign_Summary!C6 -> 2388
A6: Total Annual Revenue | B6: Annual Rev/Patient × Patients | C6: =C4*C5 -> 18626400
A7: Revenue (₹ Crore) | B7: Total Revenue / 1,00,00,000 | C7: =C6/10000000 -> 1.86264
A9: Source: Avg diabetes medicine cost — IMS Health / NPPA drug pricing, 2024 estimates

Sheet ROI_Model
A1: 📈 ROI Model — Campaign Return on Investment
A2: Metric | B2: Source / Formula | C2: Value
A3: Total Campaign Cost | B3: Linked from Campaign_Summary | C3: =Campaign_Summary!C7 -> 2018000
A4: Total Revenue Generated | B4: Linked from Revenue_Model | C4: =Revenue_Model!C6 -> 18626400
A5: Profit / (Loss) | B5: Revenue − Cost | C5: =C4-C3 -> 16608400
A6: ROI % | B6: (Profit / Cost) × 100 | C6: =IF(C3=0,0,(C5/C3)) -> 8.2301288
A7: Revenue-to-Cost Ratio | B7: Revenue ÷ Cost | C7: =IF(C3=0,0,C4/C3) -> 9.2301288
A8: Break-Even Patients | B8: Cost ÷ Annual Rev/Patient | C8: =IF(Revenue_Model!C4=0,0,C3/Revenue_Model!C4) -> 258.71795
A10: ROI Interpretation:
A11: =IF(C6>1,"✅ Campaign is profitable — Revenue exceeds Cost","⚠️ Campaign cost exceeds revenue — Review strategy") -> ✅ Campaign is profitable — Revenue exceeds Cost

Sheet Dashboard
A1: 🏥 Diabetes Campaign — Executive Dashboard | R1: Stage | S1: Count
A2: Total Reached | C2: Total Screened | E2: Diagnosed | G2: Treated | I2: Campaign Cost | K2: Total Revenue | M2: ROI % | R2: People Reached | S2: =Campaign_Summary!C3 -> 129300
A3: =Campaign_Summary!C3 -> 129300 | C3: =Campaign_Summary!C4 -> 22420 | E3: =Campaign_Summary!C5 -> 3865 | G3: =Campaign_Summary!C6 -> 2388 | I3: =Campaign_Summary!C7 -> 2018000 | K3: =Revenue_Model!C6 -> 18626400 | M3: =ROI_Model!C6 -> 8.2301288 | R3: People Screened | S3: =Campaign_Summary!C4 -> 22420
R4: Diagnosed | S4: =Campaign_Summary!C5 -> 3865
R5: Treated | S5: =Campaign_Summary!C6 -> 2388
R7: Metric | S7: Amount (₹)
R8: Total Campaign Cost | S8: =Campaign_Summary!C7 -> 2018000
R9: Total Revenue | S9: =Revenue_Model!C6 -> 18626400
R10: Profit | S10: =ROI_Model!C5 -> 16608400
